MANIFEST.in
README.rst
setup.py
textshare/SprungeSharer.py
textshare/TextSharer.py
textshare/__init__.py
textshare/command_line.py
textshare.egg-info/PKG-INFO
textshare.egg-info/SOURCES.txt
textshare.egg-info/dependency_links.txt
textshare.egg-info/entry_points.txt
textshare.egg-info/not-zip-safe
textshare.egg-info/pbr.json
textshare.egg-info/requires.txt
textshare.egg-info/top_level.txt