Metadata-Version: 1.0
Name: textshare
Version: 0.6
Summary: share your text files easily
Home-page: https://github.com/bindingofisaac/textshare
Author: Vivek
Author-email: bindingofisaacs@gmail.com
License: MIT
Platform: UNKNOWN
